task_butler/__init__.py
task_butler/config.py
task_butler/ai/__init__.py
task_butler/ai/analyzer.py
task_butler/ai/base.py
task_butler/ai/model_manager.py
task_butler/ai/planner.py
task_butler/ai/suggester.py
task_butler/ai/providers/__init__.py
task_butler/ai/providers/llama.py
task_butler/ai/providers/rule_based.py
task_butler/cli/__init__.py
task_butler/cli/completion.py
task_butler/cli/date_picker.py
task_butler/cli/main.py
task_butler/cli/commands/__init__.py
task_butler/cli/commands/add.py
task_butler/cli/commands/ai_cmd.py
task_butler/cli/commands/analyze.py
task_butler/cli/commands/config_cmd.py
task_butler/cli/commands/list_cmd.py
task_butler/cli/commands/obsidian.py
task_butler/cli/commands/plan.py
task_butler/cli/commands/show.py
task_butler/cli/commands/status.py
task_butler/cli/commands/suggest.py
task_butler/core/__init__.py
task_butler/core/recurrence.py
task_butler/core/task_manager.py
task_butler/models/__init__.py
task_butler/models/enums.py
task_butler/models/task.py
task_butler/storage/__init__.py
task_butler/storage/markdown.py
task_butler/storage/obsidian.py
task_butler/storage/repository.py
markdown_task_butler-0.2.7.dist-info/METADATA
markdown_task_butler-0.2.7.dist-info/WHEEL
markdown_task_butler-0.2.7.dist-info/entry_points.txt
markdown_task_butler-0.2.7.dist-info/RECORD
