Metadata-Version: 2.4
Name: markdown-task-butler
Version: 0.2.7
Summary: A task management tool that helps prioritize and recommend actions - your digital butler for tasks
Project-URL: Homepage, https://github.com/dobachi/task-butler
Project-URL: Repository, https://github.com/dobachi/task-butler
Project-URL: Issues, https://github.com/dobachi/task-butler/issues
Author: dobachi
License: MIT
Keywords: cli,markdown,obsidian,productivity,task,todo
Classifier: Development Status :: 4 - Beta
Classifier: Environment :: Console
Classifier: Intended Audience :: Developers
Classifier: License :: OSI Approved :: MIT License
Classifier: Operating System :: OS Independent
Classifier: Programming Language :: Python :: 3
Classifier: Programming Language :: Python :: 3.11
Classifier: Programming Language :: Python :: 3.12
Classifier: Programming Language :: Python :: 3.13
Classifier: Topic :: Utilities
Requires-Python: >=3.11
Requires-Dist: pydantic>=2.0.0
Requires-Dist: python-frontmatter>=1.0.0
Requires-Dist: rich>=13.0.0
Requires-Dist: tomli-w>=1.0.0
Requires-Dist: typer>=0.9.0
Provides-Extra: llm
Requires-Dist: llama-cpp-python>=0.2.0; extra == 'llm'
Provides-Extra: openai
Requires-Dist: openai>=1.0.0; extra == 'openai'
